sqlite_fsm_storage/__init__.py
sqlite_fsm_storage/sqlite_storage.py
sqlite_fsm_storage-2.0.4.dist-info/METADATA
sqlite_fsm_storage-2.0.4.dist-info/WHEEL
sqlite_fsm_storage-2.0.4.dist-info/top_level.txt
sqlite_fsm_storage-2.0.4.dist-info/RECORD
