Metadata-Version: 2.1
Name: sqlite-fsm-storage
Version: 2.0.4
Summary: SQLiteStorage is a very good FSM Storage for Telegram bots.
Author: EgorBlaze
Author-email: blazeegor@gmail.com
License: Apache License, Version 2.0, see LICENSE file
Requires-Dist: aiogram
Requires-Dist: aiosqlite
